spectral_energy_distribution_units/__init__.py
spectral_energy_distribution_units/_convert_units.py
spectral_energy_distribution_units/version.py
spectral_energy_distribution_units/resources/crab_sed.txt
spectral_energy_distribution_units/resources/fermi_lat_broadband_sensitivity.txt
spectral_energy_distribution_units_sebastian_achim_mueller-0.0.7.dist-info/LICENSE
spectral_energy_distribution_units_sebastian_achim_mueller-0.0.7.dist-info/METADATA
spectral_energy_distribution_units_sebastian_achim_mueller-0.0.7.dist-info/WHEEL
spectral_energy_distribution_units_sebastian_achim_mueller-0.0.7.dist-info/top_level.txt
spectral_energy_distribution_units_sebastian_achim_mueller-0.0.7.dist-info/RECORD
