Metadata-Version: 2.1
Name: spectral_energy_distribution_units_sebastian-achim-mueller
Version: 0.0.7
Summary: Converting units in Spectral-Energy-Distributions.
Home-page: https://github.com/cherenkov-plenoscope/spectral_energy_distribution_units
Author: Sebastian Achim Mueller
Author-email: sebastian-achim.mueller@mpi-hd.mpg.de
Classifier: Programming Language :: Python :: 3
Classifier: License :: OSI Approved :: MIT License
Classifier: Operating System :: OS Independent
Classifier: Natural Language :: English
Classifier: Intended Audience :: Science/Research
Classifier: Topic :: Scientific/Engineering :: Physics
Classifier: Topic :: Scientific/Engineering :: Astronomy
Requires-Python: >=3
License-File: LICENSE
Requires-Dist: numpy
